<?xml version="1.0"?>
<RBProject version="2008r5">
<block type="Module" ID="74822177">
 <ObjName>rbrwBlockSupport</ObjName>
 <ObjContainerID>-1074030850</ObjContainerID>
 <IsClass>0</IsClass>
 <ItemFlags>1</ItemFlags>
 <IsInterface>0</IsInterface>
 <Compatibility></Compatibility>
 <Method>
  <ItemName>operator_convert</ItemName>
  <Compatibility></Compatibility>
  <Visible>1</Visible>
  <ItemSource>
   <TextEncoding>134217984</TextEncoding>
   <SourceLine>Function operator_convert(extends src as rbrwSource) As rbrwBlock</SourceLine>
   <SourceLine>return new rbrwTextBlock(src)</SourceLine>
   <SourceLine>End Function</SourceLine>
  </ItemSource>
  <TextEncoding>134217984</TextEncoding>
  <AliasName></AliasName>
  <ItemFlags>0</ItemFlags>
  <Shared>0</Shared>
  <ItemParams>extends src as rbrwSource</ItemParams>
  <ItemResult>rbrwBlock</ItemResult>
 </Method>
 <ViewBehavior>
  <ViewProperty>
   <ObjName>Name</ObjName>
   <Visible>1</Visible>
   <PropertyGroup>ID</PropertyGroup>
   <InheritsFrom>Object</InheritsFrom>
  </ViewProperty>
  <ViewProperty>
   <ObjName>Index</ObjName>
   <Visible>1</Visible>
   <PropertyGroup>ID</PropertyGroup>
   <PropertyValue>2147483648</PropertyValue>
   <InheritsFrom>Object</InheritsFrom>
  </ViewProperty>
  <ViewProperty>
   <ObjName>Super</ObjName>
   <Visible>1</Visible>
   <PropertyGroup>ID</PropertyGroup>
   <InheritsFrom>Object</InheritsFrom>
  </ViewProperty>
  <ViewProperty>
   <ObjName>Left</ObjName>
   <Visible>1</Visible>
   <PropertyGroup>Position</PropertyGroup>
   <PropertyValue>0</PropertyValue>
   <InheritsFrom>Object</InheritsFrom>
  </ViewProperty>
  <ViewProperty>
   <ObjName>Top</ObjName>
   <Visible>1</Visible>
   <PropertyGroup>Position</PropertyGroup>
   <PropertyValue>0</PropertyValue>
   <InheritsFrom>Object</InheritsFrom>
  </ViewProperty>
 </ViewBehavior>
</block>
</RBProject>
