<?xml version="1.0"?>
<RBProject version="2008r4.1">
<block type="Module" ID="625222139">
 <ObjName>rbrwBreakEveryRecord</ObjName>
 <ObjContainerID>829411841</ObjContainerID>
 <IsClass>1</IsClass>
 <Superclass>rbrwBreak</Superclass>
 <ItemFlags>1</ItemFlags>
 <IsInterface>0</IsInterface>
 <Compatibility></Compatibility>
 <Method>
  <ItemName>clone</ItemName>
  <Compatibility></Compatibility>
  <Visible>1</Visible>
  <ItemSource>
   <TextEncoding>134217984</TextEncoding>
   <SourceLine>Function clone() As rbrwBreakEveryRecord</SourceLine>
   <SourceLine>return new rbrwBreakEveryRecord(self)</SourceLine>
   <SourceLine>End Function</SourceLine>
  </ItemSource>
  <TextEncoding>134217984</TextEncoding>
  <AliasName></AliasName>
  <ItemFlags>0</ItemFlags>
  <Shared>0</Shared>
  <ItemParams></ItemParams>
  <ItemResult>rbrwBreakEveryRecord</ItemResult>
 </Method>
 <Method>
  <ItemName>breaks</ItemName>
  <Compatibility></Compatibility>
  <Visible>1</Visible>
  <ItemSource>
   <TextEncoding>134217984</TextEncoding>
   <SourceLine>Function breaks() As boolean</SourceLine>
   <SourceLine>return true</SourceLine>
   <SourceLine>End Function</SourceLine>
  </ItemSource>
  <TextEncoding>134217984</TextEncoding>
  <AliasName></AliasName>
  <ItemFlags>0</ItemFlags>
  <Shared>0</Shared>
  <ItemParams></ItemParams>
  <ItemResult>boolean</ItemResult>
 </Method>
 <ViewBehavior>
  <ViewProperty>
   <ObjName>Name</ObjName>
   <Visible>1</Visible>
   <PropertyGroup>ID</PropertyGroup>
   <InheritsFrom>Object</InheritsFrom>
  </ViewProperty>
  <ViewProperty>
   <ObjName>Index</ObjName>
   <Visible>1</Visible>
   <PropertyGroup>ID</PropertyGroup>
   <PropertyValue>2147483648</PropertyValue>
   <InheritsFrom>Object</InheritsFrom>
  </ViewProperty>
  <ViewProperty>
   <ObjName>Super</ObjName>
   <Visible>1</Visible>
   <PropertyGroup>ID</PropertyGroup>
   <InheritsFrom>Object</InheritsFrom>
  </ViewProperty>
  <ViewProperty>
   <ObjName>Left</ObjName>
   <Visible>1</Visible>
   <PropertyGroup>Position</PropertyGroup>
   <PropertyValue>0</PropertyValue>
   <InheritsFrom>Object</InheritsFrom>
  </ViewProperty>
  <ViewProperty>
   <ObjName>Top</ObjName>
   <Visible>1</Visible>
   <PropertyGroup>Position</PropertyGroup>
   <PropertyValue>0</PropertyValue>
   <InheritsFrom>Object</InheritsFrom>
  </ViewProperty>
 </ViewBehavior>
</block>
</RBProject>
